fairml/__init__.py
fairml/fairness.py
fairml_garvit-0.1.0.dist-info/METADATA
fairml_garvit-0.1.0.dist-info/WHEEL
fairml_garvit-0.1.0.dist-info/top_level.txt
fairml_garvit-0.1.0.dist-info/RECORD
