Metadata-Version: 2.4
Name: fairml-garvit
Version: 0.1.0
Summary: A fairness-aware ML algorithm package
Home-page: https://github.com/yourusername/fairml
Author: Your Name
Requires-Python: >=3.7
Requires-Dist: numpy
Requires-Dist: torch
Requires-Dist: scikit-learn
Dynamic: author
Dynamic: home-page
Dynamic: requires-dist
Dynamic: requires-python
Dynamic: summary
